nsidc/__init__.py
nsidc/metgen/__init__.py
nsidc/metgen/aws.py
nsidc/metgen/cli.py
nsidc/metgen/collection_metadata.py
nsidc/metgen/config.py
nsidc/metgen/constants.py
nsidc/metgen/json-schema/cumulus_sns_schema.json
nsidc/metgen/json-schema/umm-g-json-schema.json
nsidc/metgen/lab/OLVIS1A.md
nsidc/metgen/lab/POLYGON_COMPARISON.md
nsidc/metgen/lab/README.md
nsidc/metgen/lab/__init__.py
nsidc/metgen/lab/olvis1a_processor.py
nsidc/metgen/lab/polygon_driver.py
nsidc/metgen/lab/spatial_cli.py
nsidc/metgen/lab/spatial_utils.py
nsidc/metgen/metgen.py
nsidc/metgen/models.py
nsidc/metgen/readers/__init__.py
nsidc/metgen/readers/generic.py
nsidc/metgen/readers/netcdf_reader.py
nsidc/metgen/readers/registry.py
nsidc/metgen/readers/utilities.py
nsidc/metgen/spatial/README.md
nsidc/metgen/spatial/__init__.py
nsidc/metgen/spatial/polygon_generator.py
nsidc/metgen/templates/cnm_body_template.txt
nsidc/metgen/templates/cnm_files_template.txt
nsidc/metgen/templates/ummg_additional_attributes_template.txt
nsidc/metgen/templates/ummg_body_template.txt
nsidc/metgen/templates/ummg_horizontal_gpolygon_template.txt
nsidc/metgen/templates/ummg_horizontal_orbit_template.txt
nsidc/metgen/templates/ummg_horizontal_point_template.txt
nsidc/metgen/templates/ummg_horizontal_rectangle_template.txt
nsidc/metgen/templates/ummg_temporal_range_template.txt
nsidc/metgen/templates/ummg_temporal_single_template.txt
tests/__init__.py
tests/conftest.py
tests/integration/README.md
tests/integration/__init__.py
tests/integration/configs/IPFLT1B_DUCk.ini
tests/integration/configs/IRTIT3DUCk.ini
tests/integration/configs/IRWIS2DUCk.ini
tests/integration/configs/LVISF2_DUCk.ini
tests/integration/configs/NSIDC-0081DUCk.ini
tests/integration/configs/NSIDC-0630DUCk.ini
tests/integration/configs/OLVIS1A_DUCk.ini
tests/integration/run_integration_tests.py
tests/test_aws.py
tests/test_cli.py
tests/test_collection_metadata.py
tests/test_config.py
tests/test_generic_reader.py
tests/test_metgen.py
nsidc_metgenc-1.12.0.dist-info/LICENSE.md
nsidc_metgenc-1.12.0.dist-info/METADATA
nsidc_metgenc-1.12.0.dist-info/WHEEL
nsidc_metgenc-1.12.0.dist-info/entry_points.txt
nsidc_metgenc-1.12.0.dist-info/RECORD
