Metadata-Version: 2.1
Name: nsidc-metgenc
Version: 1.12.0
Summary: The nsidc-metgenc package enables data producers as well as Operations staff managing the data ingest workflow to create metadata files conforming to NASA's Common Metadata Repository UMM-G specification.
Author: National Snow and Ice Data Center (NSIDC)
Author-email: nsidc@nsidc.org
Requires-Python: >=3.12,<4.0
Classifier: Programming Language :: Python :: 3
Classifier: Programming Language :: Python :: 3.12
Requires-Dist: alphashape (>=1.3.1,<2.0.0)
Requires-Dist: boto3 (>=1.35.22,<2.0.0)
Requires-Dist: check-jsonschema (>=0.29.4,<0.30.0)
Requires-Dist: click (>=8.1.7,<9.0.0)
Requires-Dist: concave-hull (>=0.0.9,<0.0.10)
Requires-Dist: earthaccess (>=0.14.0,<0.15.0)
Requires-Dist: funcy (>=2.0,<3.0)
Requires-Dist: geopandas (>=1.1.0,<2.0.0)
Requires-Dist: isoduration (>=20.11.0,<21.0.0)
Requires-Dist: jsonschema (>=4.23.0,<5.0.0)
Requires-Dist: netCDF4 (>=1.6.5,<2.0.0)
Requires-Dist: pandas (>=2.2.3,<3.0.0)
Requires-Dist: pyfiglet (>=1.0.2,<2.0.0)
Requires-Dist: pyproj (>=3.7.0,<4.0.0)
Requires-Dist: returns (>=0.23.0,<0.24.0)
Requires-Dist: rich (>=13.7.1,<14.0.0)
Requires-Dist: shapely (>=2.0.6,<3.0.0)
Requires-Dist: toolz (>=1.0.0,<2.0.0)
Requires-Dist: xarray (>=2024.09.0,<2025.0.0)
